<DocInternals>
  <AlwaysLoose></AlwaysLoose>
  <FieldSrcTables></FieldSrcTables>
  <TableViewData></TableViewData>
  <Bookmarks></Bookmarks>
  <SavedByVersion>11.20.11922.0409</SavedByVersion>
  <ForceBackEndMacroExecution>false</ForceBackEndMacroExecution>
  <FieldTags>
    <ScriptBased>
      <FieldTagData>
        <Tag>$hidden</Tag>
        <FieldNames>
          <String>$Field</String>
          <String>$Table</String>
          <String>$Rows</String>
          <String>$Fields</String>
          <String>$FieldNo</String>
          <String>$Info</String>
        </FieldNames>
      </FieldTagData>
      <FieldTagData>
        <Tag>$system</Tag>
        <FieldNames>
          <String>$Field</String>
          <String>$Table</String>
          <String>$Rows</String>
          <String>$Fields</String>
          <String>$FieldNo</String>
          <String>$Info</String>
        </FieldNames>
      </FieldTagData>
      <FieldTagData>
        <Tag>$ascii</Tag>
        <FieldNames>
          <String>$Field</String>
          <String>$Table</String>
          <String>$Rows</String>
          <String>$Fields</String>
          <String>$FieldNo</String>
          <String>$Info</String>
        </FieldNames>
      </FieldTagData>
      <FieldTagData>
        <Tag>$text</Tag>
        <FieldNames>
          <String>$Field</String>
          <String>$Table</String>
          <String>$Rows</String>
          <String>$Fields</String>
          <String>$FieldNo</String>
          <String>$Info</String>
        </FieldNames>
      </FieldTagData>
    </ScriptBased>
    <Interactive></Interactive>
  </FieldTags>
  <FieldComments></FieldComments>
  <TableComments></TableComments>
  <CreatePrjFolder>false</CreatePrjFolder>
  <LinkedTables></LinkedTables>
</DocInternals>
